kolena_agents/__init__.py
kolena_agents/_generated/.openapi-generator/FILES
kolena_agents/_generated/.openapi-generator/VERSION
kolena_agents/_generated/.openapi-generator-ignore
kolena_agents/_generated/__init__.py
kolena_agents/_generated/openapi_client/__init__.py
kolena_agents/_generated/openapi_client/api/__init__.py
kolena_agents/_generated/openapi_client/api/access_logs_api.py
kolena_agents/_generated/openapi_client/api/agents_api.py
kolena_agents/_generated/openapi_client/api/client_api.py
kolena_agents/_generated/openapi_client/api/workspaces_api.py
kolena_agents/_generated/openapi_client/api_client.py
kolena_agents/_generated/openapi_client/api_response.py
kolena_agents/_generated/openapi_client/configuration.py
kolena_agents/_generated/openapi_client/exceptions.py
kolena_agents/_generated/openapi_client/models/__init__.py
kolena_agents/_generated/openapi_client/models/access_log_event.py
kolena_agents/_generated/openapi_client/models/agent.py
kolena_agents/_generated/openapi_client/models/agent_credit_usage.py
kolena_agents/_generated/openapi_client/models/agent_run.py
kolena_agents/_generated/openapi_client/models/agent_run_result.py
kolena_agents/_generated/openapi_client/models/agent_run_result_metadata.py
kolena_agents/_generated/openapi_client/models/agent_run_result_metadata_citation.py
kolena_agents/_generated/openapi_client/models/agent_run_result_metadata_url_citation.py
kolena_agents/_generated/openapi_client/models/agent_run_status.py
kolena_agents/_generated/openapi_client/models/cell_result_user_data.py
kolena_agents/_generated/openapi_client/models/cell_result_user_input.py
kolena_agents/_generated/openapi_client/models/client_query_access_logs_request.py
kolena_agents/_generated/openapi_client/models/client_query_access_logs_response.py
kolena_agents/_generated/openapi_client/models/client_time_range.py
kolena_agents/_generated/openapi_client/models/copy_agent_request.py
kolena_agents-0.9.1.dist-info/METADATA
kolena_agents-0.9.1.dist-info/WHEEL
kolena_agents-0.9.1.dist-info/entry_points.txt
kolena_agents-0.9.1.dist-info/licenses/LICENSE
kolena_agents-0.9.1.dist-info/RECORD
