Metadata-Version: 2.4
Name: kolena-agents
Version: 0.9.1
Summary: Kolena Agents Client
License: Apache-2.0
License-File: LICENSE
Author: Kolena Engineering
Author-email: eng@kolena.com
Requires-Python: >=3.8,<4
Classifier: License :: OSI Approved :: Apache Software License
Classifier: Programming Language :: Python :: 3
Classifier: Programming Language :: Python :: 3.8
Classifier: Programming Language :: Python :: 3.9
Classifier: Programming Language :: Python :: 3.10
Classifier: Programming Language :: Python :: 3.11
Classifier: Programming Language :: Python :: 3.12
Classifier: Programming Language :: Python :: 3.13
Classifier: Programming Language :: Python :: 3.14
Requires-Dist: pydantic (>=2,<3)
Requires-Dist: python-dateutil (>=2.8.2,<3)
Requires-Dist: sseclient-py (>=1.8.0,<2.0.0)
Requires-Dist: urllib3 (>=1.25.3,<3)
